music_debugger/__init__.py
music_debugger/deezer.py
music_debugger/soundcloud.py
music_debugger-0.0.1.dist-info/METADATA
music_debugger-0.0.1.dist-info/WHEEL
music_debugger-0.0.1.dist-info/top_level.txt
music_debugger-0.0.1.dist-info/RECORD
