Metadata-Version: 2.1
Name: music-debugger
Version: 0.0.1
Summary: Music debugger
Author: sldless
License: MIT
Classifier: Programming Language :: Python :: 3
Classifier: License :: OSI Approved :: MIT License
Classifier: Operating System :: OS Independent
Requires-Python: >=3.8
Requires-Dist: beautifulsoup4
Requires-Dist: requests
